build/lib/build/lib/build/lib/build/lib/structs/__init__.py
build/lib/build/lib/build/lib/build/lib/structs/numpy.py
build/lib/build/lib/build/lib/build/lib/structs/struct.py
build/lib/build/lib/build/lib/build/lib/structs/torch.py
build/lib/build/lib/build/lib/structs/__init__.py
build/lib/build/lib/build/lib/structs/numpy.py
build/lib/build/lib/build/lib/structs/struct.py
build/lib/build/lib/build/lib/structs/torch.py
build/lib/build/lib/structs/__init__.py
build/lib/build/lib/structs/numpy.py
build/lib/build/lib/structs/struct.py
build/lib/build/lib/structs/torch.py
build/lib/structs/__init__.py
build/lib/structs/numpy.py
build/lib/structs/struct.py
build/lib/structs/torch.py
structs/__init__.py
structs/numpy.py
structs/struct.py
structs/torch.py
py_structs-0.2.10.dist-info/METADATA
py_structs-0.2.10.dist-info/WHEEL
py_structs-0.2.10.dist-info/top_level.txt
py_structs-0.2.10.dist-info/RECORD
