Metadata-Version: 2.1
Name: py-structs
Version: 0.2.10
Summary: Python structs and tables using dot notation
Home-page: https://github.com/saulzar/structs
Author: Oliver Batchelor
Author-email: saulzar@gmail.com
License: UNKNOWN
Platform: UNKNOWN
Classifier: Programming Language :: Python :: 3
Classifier: License :: OSI Approved :: MIT License
Classifier: Operating System :: OS Independent
Requires-Python: >=3.6
